sutd/tts/__init__.py
sutd_tts_lib-0.1.1.dist-info/WHEEL
sutd_tts_lib-0.1.1.dist-info/METADATA
sutd_tts_lib-0.1.1.dist-info/RECORD
