Metadata-Version: 2.1
Name: sutd-tts-lib
Version: 0.1.1
Summary: A (relatively) lightweight library for programmatically submitting entries to SUTD's Temperature Taking System, without Selenium and the like.
Home-page: https://github.com/chesnutcase/sutd-tts-lib
Author: Chester
Author-email: chester8991@gmail.com
Requires-Python: >=3.8,<4.0
Classifier: Programming Language :: Python :: 3
Classifier: Programming Language :: Python :: 3.8
Requires-Dist: beautifulsoup4 (>=4.9.1,<5.0.0)
Requires-Dist: fake-headers (>=1.0.2,<2.0.0)
Requires-Dist: requests (>=2.24.0,<3.0.0)
Project-URL: Repository, https://github.com/chesnutcase/sutd-tts-lib
